{
  "main": {
    "id": "89a5c4113c622535",
    "type": "split",
    "children": [
      {
        "id": "58802d5729583f18",
        "type": "tabs",
        "children": [
          {
            "id": "bd5bc0310840e570",
            "type": "leaf",
            "pinned": true,
            "state": {
              "type": "markdown",
              "state": {
                "file": "Web Servers/Nginx/Nginx Config File.md",
                "mode": "source",
                "source": false
              },
              "pinned": true,
              "icon": "lucide-file",
              "title": "Nginx Config File"
            }
          },
          {
            "id": "6733437a34c8f5f4",
            "type": "leaf",
            "state": {
              "type": "markdown",
              "state": {
                "file": "Web Servers/HTTP.md",
                "mode": "source",
                "source": false
              },
              "icon": "lucide-file",
              "title": "HTTP"
            }
          },
          {
            "id": "88534d81dd447147",
            "type": "leaf",
            "state": {
              "type": "markdown",
              "state": {
                "file": "Linux Command/Linux komutları.md",
                "mode": "source",
                "source": false
              },
              "icon": "lucide-file",
              "title": "Linux komutları"
            }
          },
          {
            "id": "964e9d0e108f0766",
            "type": "leaf",
            "state": {
              "type": "markdown",
              "state": {
                "file": "Archlinux/Archlinux Kurulum.md",
                "mode": "source",
                "source": false
              },
              "icon": "lucide-file",
              "title": "Archlinux Kurulum"
            }
          }
        ],
        "currentTab": 3
      }
    ],
    "direction": "vertical"
  },
  "left": {
    "id": "d5556bf1a29019bd",
    "type": "split",
    "children": [
      {
        "id": "b4564d569f5d8867",
        "type": "tabs",
        "children": [
          {
            "id": "f36ea74e416a148d",
            "type": "leaf",
            "state": {
              "type": "file-explorer",
              "state": {
                "sortOrder": "alphabetical"
              },
              "icon": "lucide-folder-closed",
              "title": "Files"
            }
          },
          {
            "id": "cf4a75b75808d0d3",
            "type": "leaf",
            "state": {
              "type": "search",
              "state": {
                "query": "",
                "matchingCase": false,
                "explainSearch": false,
                "collapseAll": false,
                "extraContext": false,
                "sortOrder": "alphabetical"
              },
              "icon": "lucide-search",
              "title": "Search"
            }
          },
          {
            "id": "556592daf3366e79",
            "type": "leaf",
            "state": {
              "type": "bookmarks",
              "state": {},
              "icon": "lucide-bookmark",
              "title": "Bookmarks"
            }
          }
        ]
      }
    ],
    "direction": "horizontal",
    "width": 204.5
  },
  "right": {
    "id": "1413189cf439f38e",
    "type": "split",
    "children": [
      {
        "id": "4405787cda20666b",
        "type": "tabs",
        "children": [
          {
            "id": "3c1a7e42fde10876",
            "type": "leaf",
            "state": {
              "type": "backlink",
              "state": {
                "file": "Web Servers/Nginx/Nginx Config File.md",
                "collapseAll": true,
                "extraContext": false,
                "sortOrder": "alphabetical",
                "showSearch": false,
                "searchQuery": "",
                "backlinkCollapsed": false,
                "unlinkedCollapsed": true
              },
              "icon": "links-coming-in",
              "title": "Backlinks for Nginx Config File"
            }
          },
          {
            "id": "044ba3f2a9ffbc76",
            "type": "leaf",
            "state": {
              "type": "outgoing-link",
              "state": {
                "file": "Web Servers/Nginx/Nginx Config File.md",
                "linksCollapsed": false,
                "unlinkedCollapsed": true
              },
              "icon": "links-going-out",
              "title": "Outgoing links from Nginx Config File"
            }
          },
          {
            "id": "e5eaae6931d69487",
            "type": "leaf",
            "state": {
              "type": "tag",
              "state": {
                "sortOrder": "frequency",
                "useHierarchy": true
              },
              "icon": "lucide-tags",
              "title": "Tags"
            }
          },
          {
            "id": "fcb19dadf91e237d",
            "type": "leaf",
            "state": {
              "type": "outline",
              "state": {
                "file": "Archlinux/Archlinux Kurulum.md"
              },
              "icon": "lucide-list",
              "title": "Outline of Archlinux Kurulum"
            }
          }
        ],
        "currentTab": 3
      }
    ],
    "direction": "horizontal",
    "width": 283.5
  },
  "left-ribbon": {
    "hiddenItems": {
      "switcher:Open quick switcher": false,
      "graph:Open graph view": false,
      "canvas:Create new canvas": false,
      "daily-notes:Open today's daily note": false,
      "templates:Insert template": false,
      "command-palette:Open command palette": false
    }
  },
  "active": "964e9d0e108f0766",
  "lastOpenFiles": [
    "Windows Commands/PowerShell.md",
    "Archlinux/Archlinux Kurulum.md",
    "Archlinux",
    "Linux Command/Linux komutları.md",
    "Web Servers/Nginx/Nginx Config File.md",
    "Web Servers/HTTP.md",
    "Web Servers/Nginx/Nginx Directives.md",
    "Web Servers/Nginx/Nginx location.md",
    "Programlama/Python/Django/Django türkçe.md",
    "K8s/K8s Yükleme.md",
    "K8s/K8s giriş.md",
    "Programlama/Python/Django/Django.md",
    "Web Servers/Nginx/Quick Start.md",
    "Windows Commands/WSL2.md",
    "Linux Command/Systemd.md",
    "Web Servers/Nginx/Nginx Komutları.md",
    "Docker/Dockerfile.md",
    "Programlama/Python/Python Giriş.md",
    "K8s",
    "Windows Commands/Çalıştır.md",
    "To do.md",
    "Kısayollar/windows shortcut.md",
    "Docker/Docker Giriş.md",
    "Kısayollar",
    "Network/Network Giriş.md",
    "Windows Commands/Winget Komutları.md",
    "Programlama/Python/Django",
    "Programlama/Bash_Script/Bash Script.md",
    "Git/Git Dersi.md",
    "Programlama/Python",
    "Linux Command/Network/ip.md",
    "Network",
    "Database/NoSQL",
    "Diskler",
    "Linux Command/Güvenlik",
    "Git/images/contributor.png",
    "Git/images/contributor1.png",
    "Git/images",
    "Web Servers/Nginx/images/cache_control_no_store.png",
    "Database/PostgreSQL/Pictures/if-modified-since.png",
    "Database/PostgreSQL/Pictures/Left_Join.png",
    "Pasted image 20240810145256.png",
    "Database/PostgreSQL/Pictures/inner_join.png",
    "Database/PostgreSQL/Pictures/employee_table.png",
    "Database/PostgreSQL/Pictures/department_table.png",
    "Database/PostgreSQL/Pictures/unknown.png",
    "Untitled.canvas"
  ]
}